kids/__init__.py
kids/cmd/__init__.py
kids/cmd/cmd.py
kids/cmd/input.py
kids/cmd/menu.py
kids/cmd/msg.py
kids.cmd-0.0.5.dist-info/DESCRIPTION.rst
kids.cmd-0.0.5.dist-info/LICENSE.txt
kids.cmd-0.0.5.dist-info/METADATA
kids.cmd-0.0.5.dist-info/RECORD
kids.cmd-0.0.5.dist-info/WHEEL
kids.cmd-0.0.5.dist-info/metadata.json
kids.cmd-0.0.5.dist-info/top_level.txt
