Metadata-Version: 2.0
Name: kids.cmd
Version: 0.0.5
Summary: Kids python command line library
Home-page: http://github.com/0k/kids.cmd
Author: Valentin Lab
Author-email: valentin.lab@kalysto.org
License: UNKNOWN
Platform: UNKNOWN
Classifier: Programming Language :: Python :: 2
Classifier: Topic :: Software Development :: Libraries :: Python Modules
Classifier: Development Status :: 3 - Alpha
Classifier: License :: OSI Approved :: BSD License
Classifier: Topic :: Software Development
Classifier: Intended Audience :: Developers
Requires-Dist: docopt
Requires-Dist: kids.cache
Requires-Dist: kids.file
Requires-Dist: kids.data
Requires-Dist: kids.txt
Requires-Dist: kids.cfg>=0.0.3
Requires-Dist: kids.ansi
Requires-Dist: kids.common
